FastWrite/__init__.py
FastWrite/__main__.py
FastWrite/bleu.py
FastWrite/config.py
FastWrite/data_flow.py
FastWrite/doc_generator.py
FastWrite/file_processor.py
FastWrite/print.py
FastWrite/rouge.py
fastwrite-1.2.1.dist-info/licenses/LICENSE
fastwrite-1.2.1.dist-info/METADATA
fastwrite-1.2.1.dist-info/WHEEL
fastwrite-1.2.1.dist-info/top_level.txt
fastwrite-1.2.1.dist-info/RECORD
