Metadata-Version: 2.4
Name: FastWrite
Version: 1.2.1
Summary: A module for generating AI-based code documentation and data flow diagrams.
Author-email: R-G-KJSIT <r.giridhar@somaiya.edu>
License: MIT License
Project-URL: Homepage, https://fastwrite-py.vercel.app/
Project-URL: Repository, https://github.com/R-G-KJSIT/FastWrite
Requires-Python: >=3.11
License-File: LICENSE
Requires-Dist: groq
Requires-Dist: google-genai
Requires-Dist: requests
Requires-Dist: nltk
Requires-Dist: python-dotenv
Requires-Dist: openai
Requires-Dist: rouge_metric
Dynamic: license-file
